data/__init__.py
data/example/IWIN_raw_subset_20230807.csv.zip
gxe/__init__.py
gxe/ammi.py
gxe/gge.py
iparyield/__init__.py
iparyield/data/__init__.py
iparyield/data/example/.DS_Store
iparyield/data/example/Meteo_20221031.csv.zip
iparyield/data/example/NDVI_20221031.csv.zip
iparyield/data/example/Pheno_20221031.csv.zip
iparyield/model/__init__.py
iparyield/model/daylength.py
iparyield/model/gdd.py
iparyield/model/ipar.py
iparyield/model/ndvi.py
iparyield/model/prft.py
iparyield/model/tadjday.py
iparyield/model/tday.py
stats/__init__.py
util/__init__.py
util/figures.py
iwin-2.0.1.dist-info/LICENSE
iwin-2.0.1.dist-info/METADATA
iwin-2.0.1.dist-info/WHEEL
iwin-2.0.1.dist-info/entry_points.txt
iwin-2.0.1.dist-info/top_level.txt
iwin-2.0.1.dist-info/RECORD
