Metadata-Version: 2.1
Name: iwin
Version: 2.0.1
Summary: Library for analyzing IWIN dataset
Author-email: Ernesto Giron Echeverry <e.giron.e@gmail.com>, Urs Christoph Schulthess <U.Schulthess@cgiar.org>
Maintainer-email: Ernesto Giron <e.giron.e@gmail.com>
License: GNU GENERAL PUBLIC LICENSE
Project-URL: Homepage, https://github.com/egiron/IWIN
Project-URL: documentation, https://egiron.github.io/iwin-tutorial/
Project-URL: repository, https://github.com/egiron/iwin-tutorial
Keywords: IWIN,Multi-Environment Trial Analysis,wheat,iPAR,RUE,NDVI,BLUEs,BLUPs,Heritability,Crop modeling
Classifier: License :: Free for non-commercial use
Classifier: License :: OSI Approved :: MIT License
Classifier: Programming Language :: Python
Classifier: Programming Language :: Python :: 3
Classifier: Environment :: Console
Classifier: Framework :: Jupyter
Classifier: Intended Audience :: Developers
Classifier: Intended Audience :: Education
Classifier: Intended Audience :: End Users/Desktop
Classifier: Intended Audience :: Information Technology
Classifier: Intended Audience :: Science/Research
Classifier: Natural Language :: English
Requires-Python: >=3.7
License-File: LICENSE
Requires-Dist: numpy >=1.22.4
Requires-Dist: numba >=0.51.2
Requires-Dist: pandas >=1.5.3
Requires-Dist: scikit-learn >=1.2.2
Requires-Dist: scipy >=1.10.1
Requires-Dist: basemap >=1.3.7
Requires-Dist: basemap-data >=1.3.2
Requires-Dist: basemap-data-hires >=1.3.2
Requires-Dist: pyhull >=2015.2.1
Requires-Dist: hdbscan >=0.8.33
Requires-Dist: astral >=3.1
Requires-Dist: astropy >=4.3.1
Requires-Dist: tqdm >=4.64.0
Requires-Dist: seaborn >=0.11.0
Requires-Dist: Shapely >=1.7.1
Requires-Dist: ipython >=7.21.0
